adafruit_circuitpython_epd-2.18.dist-info/licenses/LICENSE
adafruit_epd/__init__.py
adafruit_epd/ek79686.py
adafruit_epd/epd.py
adafruit_epd/il0373.py
adafruit_epd/il0398.py
adafruit_epd/il91874.py
adafruit_epd/jd79661.py
adafruit_epd/jd79667.py
adafruit_epd/mcp_sram.py
adafruit_epd/ssd1608.py
adafruit_epd/ssd1675.py
adafruit_epd/ssd1675b.py
adafruit_epd/ssd1680.py
adafruit_epd/ssd1680b.py
adafruit_epd/ssd1681.py
adafruit_epd/ssd1683.py
adafruit_epd/uc8151d.py
adafruit_epd/uc8179.py
adafruit_epd/uc8253.py
adafruit_circuitpython_epd-2.18.dist-info/METADATA
adafruit_circuitpython_epd-2.18.dist-info/WHEEL
adafruit_circuitpython_epd-2.18.dist-info/top_level.txt
adafruit_circuitpython_epd-2.18.dist-info/RECORD
