Metadata-Version: 2.4
Name: adafruit-circuitpython-epd
Version: 2.18
Summary: CircuitPython library for EPD e-ink displays.
Author-email: Adafruit Industries <circuitpython@adafruit.com>
License: MIT
Project-URL: Homepage, https://github.com/adafruit/Adafruit_CircuitPython_EPD
Keywords: adafruit,eink,e-ink,display,epd,hardware,micropython,circuitpython
Classifier: Intended Audience :: Developers
Classifier: Topic :: Software Development :: Libraries
Classifier: Topic :: Software Development :: Embedded Systems
Classifier: Topic :: System :: Hardware
Classifier: License :: OSI Approved :: MIT License
Classifier: Programming Language :: Python :: 3
License-File: LICENSE
Requires-Dist: Adafruit-Blinka
Requires-Dist: adafruit-circuitpython-busdevice
Requires-Dist: adafruit-circuitpython-framebuf
Requires-Dist: typing-extensions~=4.0
Provides-Extra: optional
Dynamic: license-file
